pysideflask/__init__.py
PySideFlask-2.0.dist-info/LICENSE
PySideFlask-2.0.dist-info/METADATA
PySideFlask-2.0.dist-info/WHEEL
PySideFlask-2.0.dist-info/top_level.txt
PySideFlask-2.0.dist-info/RECORD
