Metadata-Version: 2.1
Name: PySideFlask
Version: 2.0
Summary: Create desktop application by using Flask and QtWebEngine
Home-page: https://github.com/MadsAndreasen/PySideFlask
Author: Mads Andreasen
Author-email: app@andreasen.cc
License: MIT
Keywords: ​GUI​,​Flask​,Qt,webview
Platform: UNKNOWN
Classifier: Development Status :: 5 - Production/Stable
Classifier: Intended Audience :: Developers
Classifier: Programming Language :: Python :: 3
Requires-Python: >=3
Requires-Dist: flask
Requires-Dist: pyside2
